ckanext_blocksmith-0.3.0-py3.10-nspkg.pth
ckanext/blocksmith/__init__.py
ckanext/blocksmith/helpers.py
ckanext/blocksmith/middleware.py
ckanext/blocksmith/plugin.py
ckanext/blocksmith/tags.py
ckanext/blocksmith/types.py
ckanext/blocksmith/utils.py
ckanext/blocksmith/assets/webassets.yml
ckanext/blocksmith/assets/css/main.css
ckanext/blocksmith/assets/css/vendor/grapes.min.css
ckanext/blocksmith/assets/css/vendor/grapesjs-component-code-editor.min.css
ckanext/blocksmith/assets/css/vendor/tabulator-theme.min.css
ckanext/blocksmith/assets/css/vendor/tabulator.min.css
ckanext/blocksmith/assets/js/blocksmith-codemirror.js
ckanext/blocksmith/assets/js/blocksmith-editor.js
ckanext/blocksmith/assets/js/blocksmith-menus-list.js
ckanext/blocksmith/assets/js/blocksmith-pages-list.js
ckanext/blocksmith/assets/js/blocksmith-slugify.js
ckanext/blocksmith/assets/js/blocksmith-snippets-list.js
ckanext/blocksmith/assets/js/vendor/codemirror6.bundle.min.js
ckanext/blocksmith/assets/js/vendor/grapes-blocks-basic.min.js
ckanext/blocksmith/assets/js/vendor/grapes-blocks-flexbox.min.js
ckanext/blocksmith/assets/js/vendor/grapes-component-code-editor.min.js
ckanext/blocksmith/assets/js/vendor/grapes-navbar.min.js
ckanext/blocksmith/assets/js/vendor/grapes-parser-postcss.min.js
ckanext/blocksmith/assets/js/vendor/grapes-plugin-forms.min.js
ckanext/blocksmith/assets/js/vendor/grapes-preset-webpage.min.js
ckanext/blocksmith/assets/js/vendor/grapes.min.js
ckanext/blocksmith/assets/js/vendor/sweetalert2.min.js
ckanext/blocksmith/assets/js/vendor/tabulator.min.js
ckanext/blocksmith/logic/__init__.py
ckanext/blocksmith/logic/action.py
ckanext/blocksmith/logic/auth.py
ckanext/blocksmith/logic/schema.py
ckanext/blocksmith/logic/validators.py
ckanext/blocksmith/migration/blocksmith/alembic.ini
ckanext/blocksmith/migration/blocksmith/env.py
ckanext/blocksmith/migration/blocksmith/script.py.mako
ckanext/blocksmith/migration/blocksmith/versions/4dda752c7953_create_blocksmith_menu_table.py
ckanext_blocksmith-0.3.0.dist-info/licenses/LICENSE
ckanext_blocksmith-0.3.0.dist-info/METADATA
ckanext_blocksmith-0.3.0.dist-info/WHEEL
ckanext_blocksmith-0.3.0.dist-info/entry_points.txt
ckanext_blocksmith-0.3.0.dist-info/namespace_packages.txt
ckanext_blocksmith-0.3.0.dist-info/top_level.txt
ckanext_blocksmith-0.3.0.dist-info/RECORD
