Metadata-Version: 2.4
Name: ckanext-blocksmith
Version: 0.3.0
Summary: A modern page builder extension for CKAN, powered by GrapesJS
Author-email: DataShades <datashades@linkdigital.com.au>, Oleksandr Cherniavskiy <mutantsan@gmail.com>, Yan Rudenko <yan.rudenko@gmail.com>
License: AGPL
Project-URL: Homepage, https://github.com/DataShades/ckanext-blocksmith
Keywords: CKAN
Classifier: Development Status :: 4 - Beta
Classifier: License :: OSI Approved :: GNU Affero General Public License v3 or later (AGPLv3+)
Classifier: Programming Language :: Python :: 3.10
Classifier: Programming Language :: Python :: 3.11
Classifier: Programming Language :: Python :: 3.12
License-File: LICENSE
Requires-Dist: beautifulsoup4<5.0.0,>=4.8.2
Provides-Extra: docs
Requires-Dist: mkdocs; extra == "docs"
Requires-Dist: mkdocs-material; extra == "docs"
Requires-Dist: mkdocstrings[python]; extra == "docs"
Dynamic: license-file
